d4k_ms_auth/__info__.py
d4k_ms_auth/__init__.py
d4k_ms_auth/api_auth.py
d4k_ms_auth/auth0_management.py
d4k_ms_auth/auth0_service.py
d4k_ms_auth-0.5.0.dist-info/licenses/LICENSE
d4k_ms_auth-0.5.0.dist-info/METADATA
d4k_ms_auth-0.5.0.dist-info/WHEEL
d4k_ms_auth-0.5.0.dist-info/top_level.txt
d4k_ms_auth-0.5.0.dist-info/RECORD
