Metadata-Version: 2.4
Name: d4k_ms_auth
Version: 0.5.0
Summary: A python package containing classes for microservice user interfces
Author: D Iberson-Hurst
Author-email: 
Classifier: Intended Audience :: Developers
Classifier: Programming Language :: Python
Classifier: Programming Language :: Python :: 3
Classifier: Programming Language :: Python :: 3.10
Classifier: Operating System :: OS Independent
Requires-Python: >=3.10
License-File: LICENSE
Requires-Dist: auth0-python>=4.7.2
Requires-Dist: Authlib>=1.6.4
Requires-Dist: d4k_ms_base>=0.4.0
Requires-Dist: fastapi>=0.121.0
Dynamic: author
Dynamic: classifier
Dynamic: description
Dynamic: description-content-type
Dynamic: license-file
Dynamic: requires-dist
Dynamic: requires-python
Dynamic: summary
